MANIFEST.in
README.rst
setup.py
sqltodict/__init__.py
sqltodict/baseconnection.py
sqltodict/exceptions.py
sqltodict/mysqlconnection.py
sqltodict/postgresqlconnection.py
sqltodict.egg-info/SOURCES.txt