Metadata-Version: 1.1
Name: sqltodict
Version: 1.0
Summary: Raw sql results returns as dictionary.
Home-page: https://github.com/RedXBeard/python-sqldict
Author: Barbaros YILDIRIM
Author-email: barbarosaliyildirim@gmail.com
License: UNKNOWN
Download-URL: https://github.com/RedXBeard/python-sqldict/tarball/1.0
Keywords: sql,dict,sql to dict,select results as dict,sql to dictionary,postgresql select as dictionary,postgress results as dict
Platform: UNKNOWN
Classifier: Intended Audience :: Developers
Classifier: Operating System :: OS Independent
Classifier: Environment :: Console
Classifier: Programming Language :: Python :: 2.7
Classifier: Natural Language :: English
Classifier: License :: OSI Approved :: GNU Library or Lesser General Public License (LGPL)
